typelang/__init__.py
typelang/__main__.py
typelang/ast_types.py
typelang/codegen_jsonschema.py
typelang/codegen_python_dataclass.py
typelang/codegen_python_pydantic.py
typelang/codegen_typescript.py
typelang/compiler.py
typelang/ir_types.py
typelang/lexer.py
typelang/parser.py
typelang/transformer.py
typelang-0.0.1.dist-info/METADATA
typelang-0.0.1.dist-info/WHEEL
typelang-0.0.1.dist-info/entry_points.txt
typelang-0.0.1.dist-info/RECORD
