Metadata-Version: 2.4
Name: typelang
Version: 0.0.1
Summary: TypeScript-flavored schema definition language for cross-platform type generation
Author-email: Hao Wu <haowu@dataset.sh>
Requires-Python: >=3.11
Requires-Dist: click>=8.0
Requires-Dist: typing-extensions>=4.0
Provides-Extra: dev
Requires-Dist: black>=23.0; extra == 'dev'
Requires-Dist: mypy>=1.0; extra == 'dev'
Requires-Dist: pytest-cov>=4.0; extra == 'dev'
Requires-Dist: pytest>=7.0; extra == 'dev'
Requires-Dist: ruff>=0.1; extra == 'dev'
